README.rst
setup.cfg
setup.py
cerda/__init__.py
cerda/errors.py
cerda/farm_watcher.py
cerda/helpers.py
cerda.egg-info/PKG-INFO
cerda.egg-info/SOURCES.txt
cerda.egg-info/dependency_links.txt
cerda.egg-info/entry_points.txt
cerda.egg-info/requires.txt
cerda.egg-info/top_level.txt
test/test_parser.py