Metadata-Version: 1.1
Name: cerda
Version: 0.1.2
Summary: An NCCA renderfarm SFTP watcher
Home-page: https://github.com/docwhite/cerda
Author: Ramon Blanquer
Author-email: blanquer.ramon@gmail.com
License: MIT
Download-URL: https://github.com/docwhite/cerda/tarball/0.1.2
Keywords: renderfarm ncca transfer files watch notification email dropbox
Platform: UNKNOWN
